TestlinkApiClient/__init__.py
TestlinkApiClient/tlxmlrpc.py
TestlinkApiClient-0.5.1.dist-info/LICENSE
TestlinkApiClient-0.5.1.dist-info/METADATA
TestlinkApiClient-0.5.1.dist-info/WHEEL
TestlinkApiClient-0.5.1.dist-info/top_level.txt
TestlinkApiClient-0.5.1.dist-info/RECORD
