Metadata-Version: 2.1
Name: TestlinkApiClient
Version: 0.5.1
Summary: TestLink API XML-RPC Client
Home-page: https://github.com/testlink-metrics/testlink-api-client
Author: Will
Author-email: v.stone@163.com
Maintainer: Will
Maintainer-email: v.stone@163.com
License: MIT
Platform: linux
